tex2jb/__init__.py
tex2jb/cli/__init__.py
tex2jb/cli/app.py
tex2jb/cli/convert.py
tex2jb/config/__init__.py
tex2jb/config/book.py
tex2jb/config/execution.py
tex2jb/config/html.py
tex2jb/config/latex.py
tex2jb/config/launch_buttons.py
tex2jb/config/parse.py
tex2jb/config/repository.py
tex2jb/config/simplified.py
tex2jb/config/sphinx/__init__.py
tex2jb/config/sphinx/config/__init__.py
tex2jb/config/sphinx/config/config.py
tex2jb/config/sphinx/config/tex_macros.py
tex2jb/config/sphinx/sphinx.py
tex2jb/context.py
tex2jb/document_structure/__init__.py
tex2jb/document_structure/chapter.py
tex2jb/document_structure/extract.py
tex2jb/document_structure/part.py
tex2jb/document_structure/section.py
tex2jb/document_structure/table_of_contents.py
tex2jb/intro.py
tex2jb/logging.py
tex2jb/logo/__init__.py
tex2jb/logo/default_favicon_svg.py
tex2jb/logo/default_logo_svg.py
tex2jb/logo/find.py
tex2jb/magic_comments/__init__.py
tex2jb/magic_comments/exercise.py
tex2jb/magic_comments/index.py
tex2jb/preprocessing/__init__.py
tex2jb/preprocessing/exercise.py
tex2jb/preprocessing/preprocess.py
tex2jb/preprocessing/tilde_suffix.py
tex2jb/static/__init__.py
tex2jb/static/create_static_dir.py
tex2jb/static/custom_admonition_css.py
tex2jb/tex_element_type/__init__.py
tex2jb/tex_element_type/get_tex_element_type.py
tex2jb/tex_element_type/tex_element_type.py
tex2jb/to_markdown/__init__.py
tex2jb/to_markdown/align.py
tex2jb/to_markdown/chapter.py
tex2jb/to_markdown/cite.py
tex2jb/to_markdown/comment.py
tex2jb/to_markdown/corollary.py
tex2jb/to_markdown/definition.py
tex2jb/to_markdown/enumerate.py
tex2jb/to_markdown/eqref.py
tex2jb/to_markdown/example.py
tex2jb/to_markdown/exercise.py
tex2jb/to_markdown/figure.py
tex2jb/to_markdown/frontmatter.py
tex2jb/to_markdown/index.py
tex2jb/to_markdown/label.py
tex2jb/to_markdown/lemma.py
tex2jb/to_markdown/mainmatter.py
tex2jb/to_markdown/note.py
tex2jb/to_markdown/part.py
tex2jb/to_markdown/printbibliography.py
tex2jb/to_markdown/printindex.py
tex2jb-0.1.0.dist-info/METADATA
tex2jb-0.1.0.dist-info/WHEEL
tex2jb-0.1.0.dist-info/entry_points.txt
tex2jb-0.1.0.dist-info/RECORD
